{
  "analysis_date": "2026-01-14T12:08:25.549600+00:00",
  "industry": "Capital Markets",
  "winners_analyzed": 4,
  "losers_analyzed": 1,
  "non_movers_analyzed": 10,
  "winners_with_data": 0,
  "losers_with_data": 0,
  "non_movers_with_data": 0,
  "thresholds": {
    "tick_density": 1.0,
    "delta_ratio": 1.0
  },
  "winner_stats": {
    "tick_density_met": 0,
    "delta_ratio_met": 0,
    "any_criteria_met": 0
  },
  "loser_stats": {
    "tick_density_met": 0,
    "delta_ratio_met": 0,
    "any_criteria_met": 0
  },
  "non_mover_stats": {
    "tick_density_met": 0,
    "delta_ratio_met": 0,
    "any_criteria_met": 0
  },
  "performance": {
    "precision": 0,
    "recall": 0,
    "false_positives": 0
  },
  "detailed_results": {
    "winners": [
      {
        "symbol": "NCPL",
        "received_at": "2026-01-06T21:22:01.945937+00:00",
        "window_seconds": 10.0,
        "spread_compression": {},
        "tick_density": {},
        "delta_ratio": {},
        "quote_frequency": {},
        "max_excursion_in_window": {},
        "data_available": false,
        "timing_analysis": {},
        "error": "No trades/quotes in window",
        "article_id": "benzinga:49740453",
        "max_excursion_pct": 14.214463840399,
        "title": "Netcapital Acquires Iverson Design Assets and Proprietary AI Design Technology Suite"
      },
      {
        "symbol": "CNCK",
        "received_at": "2026-01-08T12:00:15.713054+00:00",
        "window_seconds": 10.0,
        "spread_compression": {},
        "tick_density": {},
        "delta_ratio": {},
        "quote_frequency": {},
        "max_excursion_in_window": {},
        "data_available": false,
        "timing_analysis": {},
        "error": "No trades/quotes in window",
        "article_id": "benzinga:49778012",
        "max_excursion_pct": 27.777777777777775,
        "title": "Coincheck Group Signs Agreement to Acquire 3iQ, a Global Pioneer in Digital Asset Investment Solutio"
      },
      {
        "symbol": "SLNH",
        "received_at": "2026-01-08T12:30:03.679272+00:00",
        "window_seconds": 10.0,
        "spread_compression": {},
        "tick_density": {},
        "delta_ratio": {},
        "quote_frequency": {},
        "max_excursion_in_window": {},
        "data_available": false,
        "timing_analysis": {},
        "error": "No trades/quotes in window",
        "article_id": "benzinga:49779048",
        "max_excursion_pct": 14.942528735632186,
        "title": "Soluna and Siemens Collaborate to Solve GPU Power Swings in Behind-the-Meter AI"
      },
      {
        "symbol": "HGBL",
        "received_at": "2026-01-12T21:02:11.096930+00:00",
        "window_seconds": 10.0,
        "spread_compression": {},
        "tick_density": {},
        "delta_ratio": {},
        "quote_frequency": {},
        "max_excursion_in_window": {},
        "data_available": false,
        "timing_analysis": {},
        "error": "No trades/quotes in window",
        "article_id": "benzinga:49859894",
        "max_excursion_pct": 6.707317073170738,
        "title": "Heritage Global Inc. Acquires The Debt Exchange, Inc. (DebtX)"
      }
    ],
    "losers": [
      {
        "symbol": "CANG",
        "received_at": "2026-01-05T11:00:25.134525+00:00",
        "window_seconds": 10.0,
        "spread_compression": {},
        "tick_density": {},
        "delta_ratio": {},
        "quote_frequency": {},
        "max_excursion_in_window": {},
        "data_available": false,
        "timing_analysis": {},
        "error": "No trades/quotes in window",
        "article_id": "benzinga:49685684",
        "max_excursion_pct": -5.3333333333333375,
        "title": "Cango Inc. Announces December 2025 Bitcoin Production and Mining Operations Update"
      }
    ],
    "non_movers": [
      {
        "symbol": "DEFT",
        "received_at": "2026-01-05T14:00:50.877893+00:00",
        "window_seconds": 10.0,
        "spread_compression": {},
        "tick_density": {},
        "delta_ratio": {},
        "quote_frequency": {},
        "max_excursion_in_window": {},
        "data_available": false,
        "timing_analysis": {},
        "error": "No trades/quotes in window",
        "article_id": "benzinga:49691063",
        "max_excursion_pct": 0.4606365159128936,
        "title": "DeFi Technologies Class Action: The Gross Law Firm Reminds DeFi Technologies Investors of the Pendin"
      },
      {
        "symbol": "DEFT",
        "received_at": "2026-01-06T21:00:03.105952+00:00",
        "window_seconds": 10.0,
        "spread_compression": {},
        "tick_density": {},
        "delta_ratio": {},
        "quote_frequency": {},
        "max_excursion_in_window": {},
        "data_available": false,
        "timing_analysis": {},
        "error": "No trades/quotes in window",
        "article_id": "benzinga:49739175",
        "max_excursion_pct": -0.010752688172053763,
        "title": "DeFi Technologies Class Action: Levi &amp; Korsinsky Reminds DeFi Technologies Investors of the Pend"
      },
      {
        "symbol": "DEFT",
        "received_at": "2026-01-06T21:30:20.452912+00:00",
        "window_seconds": 10.0,
        "spread_compression": {},
        "tick_density": {},
        "delta_ratio": {},
        "quote_frequency": {},
        "max_excursion_in_window": {},
        "data_available": false,
        "timing_analysis": {},
        "error": "No trades/quotes in window",
        "article_id": "benzinga:49740694",
        "max_excursion_pct": 0.0,
        "title": "DEFT Investors Have Opportunity to Lead DeFi Technologies, Inc. Securities Fraud Lawsuit"
      },
      {
        "symbol": "MS",
        "received_at": "2026-01-06T13:05:03.506382+00:00",
        "window_seconds": 10.0,
        "spread_compression": {},
        "tick_density": {},
        "delta_ratio": {},
        "quote_frequency": {},
        "max_excursion_in_window": {},
        "data_available": false,
        "timing_analysis": {},
        "error": "No trades/quotes in window",
        "article_id": "benzinga:49719637",
        "max_excursion_pct": -0.5709711846318,
        "title": "Morgan Stanley Capital Partners Completes the Sale of Alliance Technical Group"
      },
      {
        "symbol": "BITF",
        "received_at": "2026-01-07T21:05:03.221833+00:00",
        "window_seconds": 10.0,
        "spread_compression": {},
        "tick_density": {},
        "delta_ratio": {},
        "quote_frequency": {},
        "max_excursion_in_window": {},
        "data_available": false,
        "timing_analysis": {},
        "error": "No trades/quotes in window",
        "article_id": "benzinga:49769241",
        "max_excursion_pct": 0.3571428571428654,
        "title": "Bitfarms to Present at Needham Growth Conference in NYC"
      },
      {
        "symbol": "JEF",
        "received_at": "2026-01-07T21:15:08.911285+00:00",
        "window_seconds": 10.0,
        "spread_compression": {},
        "tick_density": {},
        "delta_ratio": {},
        "quote_frequency": {},
        "max_excursion_in_window": {},
        "data_available": false,
        "timing_analysis": {},
        "error": "No trades/quotes in window",
        "article_id": "benzinga:49769803",
        "max_excursion_pct": -0.5823754789271961,
        "title": "Jefferies Announces Fourth Quarter 2025 Financial Results"
      },
      {
        "symbol": "DEFT",
        "received_at": "2026-01-07T21:15:25.360102+00:00",
        "window_seconds": 10.0,
        "spread_compression": {},
        "tick_density": {},
        "delta_ratio": {},
        "quote_frequency": {},
        "max_excursion_in_window": {},
        "data_available": false,
        "timing_analysis": {},
        "error": "No trades/quotes in window",
        "article_id": "benzinga:49769822",
        "max_excursion_pct": 0.0,
        "title": "Bragar Eagel &amp; Squire, P.C. Reminds Stockholders of Sprouts Farmers Market and DeFi Technologies"
      },
      {
        "symbol": "CIFR",
        "received_at": "2026-01-08T21:05:05.286334+00:00",
        "window_seconds": 10.0,
        "spread_compression": {},
        "tick_density": {},
        "delta_ratio": {},
        "quote_frequency": {},
        "max_excursion_in_window": {},
        "data_available": false,
        "timing_analysis": {},
        "error": "No trades/quotes in window",
        "article_id": "benzinga:49800149",
        "max_excursion_pct": -0.30211480362538196,
        "title": "Cipher Mining Announces Participation in Upcoming Investor and Industry Conferences"
      },
      {
        "symbol": "GS",
        "received_at": "2026-01-08T12:00:03.743280+00:00",
        "window_seconds": 10.0,
        "spread_compression": {},
        "tick_density": {},
        "delta_ratio": {},
        "quote_frequency": {},
        "max_excursion_in_window": {},
        "data_available": false,
        "timing_analysis": {},
        "error": "No trades/quotes in window",
        "article_id": "benzinga:49777967",
        "max_excursion_pct": -0.5734614771942842,
        "title": "Beacon Therapeutics Announces Closing of Oversubscribed Series C Financing for Over $75 Million"
      },
      {
        "symbol": "DEFT",
        "received_at": "2026-01-10T03:14:13.541931+00:00",
        "window_seconds": 10.0,
        "spread_compression": {},
        "tick_density": {},
        "delta_ratio": {},
        "quote_frequency": {},
        "max_excursion_in_window": {},
        "data_available": false,
        "timing_analysis": {},
        "error": "No trades/quotes in window",
        "article_id": "benzinga:49828599",
        "max_excursion_pct": 0.0,
        "title": "DeFi Technologies Shareholder Alert: ClaimsFiler Reminds Investors With Losses In Excess Of $100,000"
      }
    ]
  }
}